dicomdiff/__init__.py
dicomdiff/cli.py
dicomdiff/comparison.py
dicomdiff/context.py
dicomdiff/datamodel.py
dicomdiff/main.py
dicomdiff/pseudonymizer.py
dicomdiff/summary.py
dicomdiff-0.4.0.dist-info/LICENSE
dicomdiff-0.4.0.dist-info/METADATA
dicomdiff-0.4.0.dist-info/WHEEL
dicomdiff-0.4.0.dist-info/entry_points.txt
dicomdiff-0.4.0.dist-info/RECORD
