Metadata-Version: 2.3
Name: dicomdiff
Version: 0.4.0
Summary: A Python module that compares an original DICOM file with its deidentified counterpart and returns the differences between the two.
Author: Karim
Author-email: 115158216+karimdiabb@users.noreply.github.com
Requires-Python: >=3.12
Classifier: Programming Language :: Python :: 3
Classifier: Programming Language :: Python :: 3.12
Classifier: Programming Language :: Python :: 3.13
Requires-Dist: click (>=8.1.8,<9.0.0)
Requires-Dist: pandas (>=2.2.3,<3.0.0)
Requires-Dist: pydicom (>=3.0.0,<4.0.0)
Requires-Dist: pytest (>=8.3.4,<9.0.0)
Requires-Dist: tabulate (>=0.9.0,<0.10.0)
Requires-Dist: tqdm (>=4.67.1,<5.0.0)
